README.md
setup.py
pytorch_complex_tensor/__init__.py
pytorch_complex_tensor/complex_grad.py
pytorch_complex_tensor/complex_scalar.py
pytorch_complex_tensor/complex_tensor.py
pytorch_complex_tensor/torch_complex.py
pytorch_complex_tensor.egg-info/PKG-INFO
pytorch_complex_tensor.egg-info/SOURCES.txt
pytorch_complex_tensor.egg-info/dependency_links.txt
pytorch_complex_tensor.egg-info/requires.txt
pytorch_complex_tensor.egg-info/top_level.txt
tests/__init__.py
tests/pytorch_complex_tensor_test.py
tests/torch_complex_test.py