Metadata-Version: 1.0
Name: pytorch-complex-tensor
Version: 0.0.128
Summary: Pytorch complex tensor
Home-page: https://github.com/williamFalcon/pytorch-complex-tensor
Author: William Falcon
Author-email: waf2107@columbia.edu
License: UNKNOWN
Platform: UNKNOWN
